konezumiaid/DATAREADME.md
konezumiaid/create_gene_dataclass.py
konezumiaid/evaluate_grna/add_grna_info.py
konezumiaid/evaluate_grna/apply_nmd_rules.py
konezumiaid/evaluate_grna/main.py
konezumiaid/format_and_export_dataset/convert_refflat_to_bed6.py
konezumiaid/format_and_export_dataset/generate_seq_dict_from_fasta.py
konezumiaid/format_and_export_dataset/generate_sorted_genedata_from_refflat.py
konezumiaid/format_and_export_dataset/main.py
konezumiaid/format_and_export_dataset/translate_bed_from_refflat.sh
konezumiaid/format_output.py
konezumiaid/get_exon_range.py
konezumiaid/get_reverse_complement.py
konezumiaid/get_rtpcr_primer/add_uniqueness.py
konezumiaid/get_rtpcr_primer/export_fasta.py
konezumiaid/get_rtpcr_primer/get_uniqueness.sh
konezumiaid/get_rtpcr_primer/main.py
konezumiaid/get_rtpcr_primer/make_rtpcr_primer.py
konezumiaid/get_rtpcr_primer/rate_quality.py
konezumiaid/main.py
konezumiaid/nominate_ptc_guide/add_aminoacid_info.py
konezumiaid/nominate_ptc_guide/find_candidate_seq.py
konezumiaid/nominate_ptc_guide/generate_cds_seq.py
konezumiaid/nominate_ptc_guide/main.py
konezumiaid/nominate_ptc_guide/make_grna_from_position.py
konezumiaid/nominate_ptc_guide/search_candidate_codon.py
konezumiaid/nominate_ptc_guide/transform_candidateseq_to_position.py
konezumiaid/nominate_ptc_guide/translate_codon_position_to_inorf.py
konezumiaid/nominate_splicesite_guide/search_candidate.py
konezumiaid-0.3.6.1.dist-info/LICENSE
konezumiaid-0.3.6.1.dist-info/METADATA
konezumiaid-0.3.6.1.dist-info/WHEEL
konezumiaid-0.3.6.1.dist-info/entry_points.txt
konezumiaid-0.3.6.1.dist-info/RECORD
