Metadata-Version: 2.1
Name: KOnezumiAID
Version: 0.3.6.1
Summary: This is used for automatically designing gRNAs for genome editing by Target-AID.
Home-page: https://github.com/aki2274/KOnezumi-AID
License: MIT
Author: Taki Taito
Author-email: s2110307@u.tsukuba.ac.jp
Requires-Python: >=3.9,<4.0
Classifier: Intended Audience :: Science/Research
Classifier: License :: OSI Approved :: MIT License
Classifier: Operating System :: MacOS
Classifier: Operating System :: POSIX :: Linux
Classifier: Programming Language :: Python :: 3
Classifier: Programming Language :: Python :: 3.9
Classifier: Programming Language :: Python :: 3.10
Classifier: Programming Language :: Python :: 3.11
Classifier: Programming Language :: Python :: 3.12
Classifier: Programming Language :: Python :: 3.13
Classifier: Topic :: Scientific/Engineering :: Bio-Informatics
Requires-Dist: numpy (>=1.26.0,<2.0.0)
Requires-Dist: pandas (>=2.2.2,<3.0.0)
Requires-Dist: primer3-py (>=2.0.1,<3.0.0)
Requires-Dist: regex (>=2024.11.6,<2025.0.0)
